clsz/__init__.py
clsz/clsz.py
clsz/cluster.py
clsz/metrics.py
clsz-0.2.0.dist-info/DESCRIPTION.rst
clsz-0.2.0.dist-info/METADATA
clsz-0.2.0.dist-info/RECORD
clsz-0.2.0.dist-info/WHEEL
clsz-0.2.0.dist-info/metadata.json
clsz-0.2.0.dist-info/top_level.txt
